{
 "exam_id": "2022_basis",
 "track": "basis",
 "date": "2022",
 "tag_candidates": [
  "2022",
  "Jun22"
 ],
 "stats": {
  "canonical_parsed": 137,
  "canonical_with_4_opts": 118,
  "answers_parsed": 150,
  "questions_with_matches": 128,
  "questions_without_matches": 9
 },
 "findings": {
  "c_mismatches": [],
  "tag_mismatches": [],
  "no_match": [
   [
    13,
    "בן86 , הגיע למרפאה עקב תלונות על גרד ואודם ברגליים, שידוע מזה זמן רב, אך .לאחרונ"
   ],
   [
    21,
    "איזה טיפול תרופתי אינו מומלץ בקשישים על פי2019 AGS BEERS CRITERIA ? .אAmiodarone"
   ],
   [
    22,
    "מה כוללת שיטתDICE ?להתמודדות עם הפרעות התנהגות של דמנציה .אDescribe, Investigate"
   ],
   [
    24,
    "בת76 , עצמאית וללא ירידה קוגניטיבית, ברקע סוכרת, יתר לחץ דם ואוסטאוארטריטיס. תרו"
   ],
   [
    61,
    "בן88 הסובל מדמנציה מתקדמת מאושפז במחלקה לסיעוד מור כב עקב פצע לחץ המופיע בתמונה "
   ],
   [
    71,
    ". פולימורפיזם במספר גנים הוכח כקשור להארכת חיים איזה גן מהגנים הבאים לא הוכח ?כק"
   ],
   [
    95,
    "בת66 , אלמנה תשושה בתפקודה, מתגוררת בביתה, הופנתה למחלקה לרפואה דחופה עקב חום וש"
   ],
   [
    98,
    "?מי מהחולים הבאים מתאים לאשפוז במחלקה לסיעוד מורכב .א בן88 , מרותק למיטה, ניזון "
   ],
   [
    119,
    "מה השילוב הנכון בין סוג הזיהום העורי לבין חיידק הגורם לו בשכיחות גבוהה .אFollicu"
   ]
  ],
  "low_confidence": [
   {
    "q_num": 57,
    "idx": 52,
    "sim": 0.74,
    "tag": "2022"
   }
  ],
  "duplicates": [],
  "missing_ti": [],
  "truncated_q": [
   {
    "q_num": 34,
    "idx": 29,
    "ds_q_len": 38,
    "tag": "2022"
   },
   {
    "q_num": 65,
    "idx": 59,
    "ds_q_len": 39,
    "tag": "2022"
   },
   {
    "q_num": 137,
    "idx": 3486,
    "ds_q_len": 29,
    "tag": "2022"
   }
  ]
 }
}